envcrypto/__init__.py
envcrypto/base58.py
envcrypto/crypto.py
envcrypto-0.2.0.dist-info/LICENSE
envcrypto-0.2.0.dist-info/METADATA
envcrypto-0.2.0.dist-info/WHEEL
envcrypto-0.2.0.dist-info/top_level.txt
envcrypto-0.2.0.dist-info/RECORD
