Metadata-Version: 2.1
Name: envcrypto
Version: 0.2.0
Summary: A safe way to store environmental variables.
Home-page: https://github.com/fufuok/envcrypto
Author: Fufu
Author-email: fufuokok@gmail.com
License: MIT
Platform: UNKNOWN
Classifier: Operating System :: OS Independent
Classifier: Programming Language :: Python :: 3
Classifier: Topic :: Software Development :: Libraries :: Python Modules
Requires-Python: >=3.6
Requires-Dist: pycryptodome (>=3.9.8)
